{
  "project_info": {
    "project_number": "590734042791",
    "project_id": "flutter-e-commerce-app-bk",
    "storage_bucket": "flutter-e-commerce-app-bk.firebasestorage.app"
  },
  "client": [
    {
      "client_info": {
        "mobilesdk_app_id": "1:590734042791:android:1d6a803c7d4192832c5d82",
        "android_client_info": {
          "package_name": "com.bharathkumar.ecommerce_app"
        }
      },
      "oauth_client": [],
      "api_key": [
        {
          "current_key": "AIzaSyBTZ1662r5zrG7ilSIsMefxdyy5kk1EzXc"
        }
      ],
      "services": {
        "appinvite_service": {
          "other_platform_oauth_client": []
        }
      }
    }
  ],
  "configuration_version": "1"
}